README.rst
setup.py
jsonxs/__init__.py
jsonxs/jsonxs.py
jsonxs.egg-info/PKG-INFO
jsonxs.egg-info/SOURCES.txt
jsonxs.egg-info/dependency_links.txt
jsonxs.egg-info/top_level.txt
jsonxs.egg-info/zip-safe