Metadata-Version: 1.0
Name: jsonxs
Version: 0.2
Summary: Use path expression strings to get and set values in JSON
Home-page: https://github.com/fboender/jsonxs
Author: Ferry Boender
Author-email: ferry.boender@gmail.com
License: MIT
Platform: UNKNOWN
